{
  "vendors.js": "/rkta-ui/static/js/vendors.c14e5995.js",
  "vendors.js.map": "/rkta-ui/static/js/vendors.125490b67b9823d1b53e.js.map",
  "atoms-addon-addon~atoms-divider-divider~molecules-button-button~molecules-list-list~molecules-tabs-t~4699d9fd.js": "/rkta-ui/static/js/atoms-addon-addon~atoms-divider-divider~molecules-button-button~molecules-list-list~molecules-tabs-t~4699d9fd.294a37d8.js",
  "atoms-addon-addon~atoms-divider-divider~molecules-button-button~molecules-list-list~molecules-tabs-t~4699d9fd.js.map": "/rkta-ui/static/js/atoms-addon-addon~atoms-divider-divider~molecules-button-button~molecules-list-list~molecules-tabs-t~4699d9fd.125490b67b9823d1b53e.js.map",
  "app.js": "/rkta-ui/static/js/app.3acb5bcb.js",
  "app.js.map": "/rkta-ui/static/js/app.125490b67b9823d1b53e.js.map",
  "atoms-addon-addon.js": "/rkta-ui/static/js/atoms-addon-addon.ef6cc157.js",
  "atoms-addon-addon.js.map": "/rkta-ui/static/js/atoms-addon-addon.125490b67b9823d1b53e.js.map",
  "atoms-atom-atom.js": "/rkta-ui/static/js/atoms-atom-atom.50e778ef.js",
  "atoms-atom-atom.js.map": "/rkta-ui/static/js/atoms-atom-atom.125490b67b9823d1b53e.js.map",
  "atoms-bage-bage.js": "/rkta-ui/static/js/atoms-bage-bage.61a52efb.js",
  "atoms-bage-bage.js.map": "/rkta-ui/static/js/atoms-bage-bage.125490b67b9823d1b53e.js.map",
  "atoms-divider-divider.js": "/rkta-ui/static/js/atoms-divider-divider.b6c64e07.js",
  "atoms-divider-divider.js.map": "/rkta-ui/static/js/atoms-divider-divider.125490b67b9823d1b53e.js.map",
  "index.js": "/rkta-ui/static/js/index.05554766.js",
  "index.js.map": "/rkta-ui/static/js/index.125490b67b9823d1b53e.js.map",
  "molecules-button-button.js": "/rkta-ui/static/js/molecules-button-button.f53aeebc.js",
  "molecules-button-button.js.map": "/rkta-ui/static/js/molecules-button-button.125490b67b9823d1b53e.js.map",
  "molecules-list-list.js": "/rkta-ui/static/js/molecules-list-list.7930e6be.js",
  "molecules-list-list.js.map": "/rkta-ui/static/js/molecules-list-list.125490b67b9823d1b53e.js.map",
  "molecules-tabs-tabs.js": "/rkta-ui/static/js/molecules-tabs-tabs.7e420b97.js",
  "molecules-tabs-tabs.js.map": "/rkta-ui/static/js/molecules-tabs-tabs.125490b67b9823d1b53e.js.map",
  "runtime~app.js": "/rkta-ui/static/js/runtime~app.125490b67b9823d1b53e.js",
  "runtime~app.js.map": "/rkta-ui/static/js/runtime~app.125490b67b9823d1b53e.js.map",
  "static/js/12.412cb451.js": "/rkta-ui/static/js/12.412cb451.js",
  "static/js/12.125490b67b9823d1b53e.js.map": "/rkta-ui/static/js/12.125490b67b9823d1b53e.js.map",
  "index.html": "/rkta-ui/index.html"
}